camelot/barbican/__init__.py
camelot/barbican/__version__.py
camelot/barbican/barbican.py
camelot/barbican/config.py
camelot/barbican/console.py
camelot/barbican/logger.py
camelot/barbican/py.typed
camelot/barbican/_internals/__init__.py
camelot/barbican/_internals/capture_out.py
camelot/barbican/_internals/cargo_config.py
camelot/barbican/_internals/cargo_install.py
camelot/barbican/_internals/gen_ldscript.py
camelot/barbican/_internals/gen_memory_layout.py
camelot/barbican/_internals/gen_task_metadata_bin.py
camelot/barbican/_internals/install.py
camelot/barbican/_internals/kernel_fixup.py
camelot/barbican/_internals/meson_package_dyndep.py
camelot/barbican/_internals/objcopy.py
camelot/barbican/_internals/relink_elf.py
camelot/barbican/_internals/srec_cat.py
camelot/barbican/buildsys/__init__.py
camelot/barbican/buildsys/ninja_backend.py
camelot/barbican/package/__init__.py
camelot/barbican/package/cargo.py
camelot/barbican/package/kernel.py
camelot/barbican/package/meson.py
camelot/barbican/package/package.py
camelot/barbican/package/runtime.py
camelot/barbican/relocation/__init__.py
camelot/barbican/relocation/elfutils.py
camelot/barbican/scm/__init__.py
camelot/barbican/scm/git.py
camelot/barbican/scm/scm.py
camelot/barbican/utils/__init__.py
camelot/barbican/utils/environment.py
camelot/barbican/utils/memory_layout.py
camelot/barbican/utils/pathhelper.py
camelot_barbican-0.4.4.dist-info/licenses/LICENSE
camelot_barbican-0.4.4.dist-info/METADATA
camelot_barbican-0.4.4.dist-info/WHEEL
camelot_barbican-0.4.4.dist-info/entry_points.txt
camelot_barbican-0.4.4.dist-info/top_level.txt
camelot_barbican-0.4.4.dist-info/RECORD
