Metadata-Version: 2.4
Name: camelot-barbican
Version: 0.4.4
Summary: Camelot-OS build system
Author: Florent Valette, Philippe Thierry
License:                                  Apache License
Project-URL: Homepage, https://github.com/camelot-os
Project-URL: Repository, https://github.com/camelot-os/barbican
Project-URL: Issues, https://github.com/camelot-os/barbican/issues
Classifier: Development Status :: 4 - Beta
Classifier: Intended Audience :: Developers
Classifier: Topic :: Software Development :: Build Tools
Classifier: License :: OSI Approved :: Apache Software License
Classifier: Programming Language :: Python :: 3
Classifier: Programming Language :: Python :: 3 :: Only
Classifier: Programming Language :: Python :: 3.10
Classifier: Programming Language :: Python :: 3.11
Classifier: Programming Language :: Python :: 3.12
Requires-Python: >=3.10
License-File: LICENSE
Requires-Dist: Jinja2>=3.1.0
Requires-Dist: jinja-cli>=1.2.0
Requires-Dist: jsonschema>=4.18.0
Requires-Dist: kconfiglib>=14.1.0
Requires-Dist: lief<0.15,>=0.13
Requires-Dist: meson>=1.7.0
Requires-Dist: ninja>=1.11.0
Requires-Dist: ninja_syntax>1.7
Requires-Dist: svd2json>=0.1.6
Requires-Dist: dts-utils>=0.2.0
Requires-Dist: tomli>=2.0.1; python_version < "3.11"
Requires-Dist: referencing>=0.33.0
Requires-Dist: rich>=13.6
Requires-Dist: GitPython>=3.1.44
Provides-Extra: devel
Requires-Dist: flake8<8.0,>=7.0; extra == "devel"
Requires-Dist: mypy>=1.12.0; extra == "devel"
Requires-Dist: pytest>=4.6; extra == "devel"
Requires-Dist: pytest-cov>=5.0.0; extra == "devel"
Requires-Dist: pytest-dependency>=0.6; extra == "devel"
Requires-Dist: black<25.0,>=24.2; extra == "devel"
Requires-Dist: pydoclint; extra == "devel"
Requires-Dist: flake8-docstrings; extra == "devel"
Requires-Dist: types-jsonschema>=4.18.0; extra == "devel"
Provides-Extra: doc
Requires-Dist: Sphinx>=7.2.0; extra == "doc"
Requires-Dist: sphinx-rtd-theme>=2.0.0; extra == "doc"
Requires-Dist: sphinx-simplepdf>=1.6.0; extra == "doc"
Requires-Dist: sphinx-autoapi; extra == "doc"
Requires-Dist: sphinx-argparse; extra == "doc"
Provides-Extra: tools
Requires-Dist: dts-utils; extra == "tools"
Requires-Dist: svd2json; extra == "tools"
Dynamic: license-file
